makefun/__init__.py
makefun/_main_legacy_py.py
makefun/_main_py35_and_higher.py
makefun/_main_py36_and_higher.py
makefun/_version.py
makefun/main.py
makefun/py.typed
makefun-1.15.4.dist-info/LICENSE
makefun-1.15.4.dist-info/METADATA
makefun-1.15.4.dist-info/WHEEL
makefun-1.15.4.dist-info/top_level.txt
makefun-1.15.4.dist-info/RECORD
